{
    "function": "bin.tune.main",
    "best": {
        "function": "bin.ffn.main",
        "devices": [
            "Tesla V100-SXM2-32GB"
        ],
        "n_parameters": 328693,
        "best_epoch": 204,
        "tuning_time": "0:32:15",
        "trial_id": 53,
        "scores": {
            "train": -0.12041884557591731,
            "val": -0.13545457559908566,
            "test": -0.13773304850051574
        },
        "time": "0:00:37"
    },
    "n_completed_trials": 84,
    "time": "0:42:48"
}
